__init__.py
solidipy/__init__.py
solidipy/constants/__init__.py
solidipy/constants/error_constants.py
solidipy/crypto/__init__.py
solidipy/exceptions/__init__.py
solidipy/exceptions/exception_handler.py
solidipy/exceptions/exception_values.py
solidipy/logging_utility/__init__.py
solidipy/logging_utility/base_logger.py
solidipy/utilities/__init__.py
solidipy/utilities/dict_utilities.py
solidipy/utilities/general_utilities.py
solidipy/utilities/list_utilities.py
solidipy/utilities/number_utilities.py
solidipy/utilities/string_utilities.py
solidipy/utilities/time_utilities.py
solidipy/utilities/http/__init__.py
solidipy/utilities/http/http_error.py
solidipy/utilities/http/http_response.py
solidipy/validation/__init__.py
solidipy/validation/validation.py
solidipy-0.4.6.dist-info/licenses/LICENSE.txt
solidipy-0.4.6.dist-info/METADATA
solidipy-0.4.6.dist-info/WHEEL
solidipy-0.4.6.dist-info/top_level.txt
solidipy-0.4.6.dist-info/RECORD
