Metadata-Version: 2.4
Name: solidipy
Version: 0.4.6
Summary: A variety of utilities for common tasks
Author: Jackson Prince, Michael Karavan, Joshua Schutza, Jacob Roscoe, Joe Vellella
Maintainer: Jackson Prince
License: Copyright (c) 2024 Wavelynx Technologies LLC
Project-URL: Source, https://gitlab.com/WaveLynxTech/solidipy
Keywords: utility,python,solidipy
Classifier: Development Status :: 4 - Beta
Classifier: Intended Audience :: Developers
Classifier: License :: OSI Approved :: MIT License
Classifier: Programming Language :: Python :: 3
Requires-Python: >=3.10
License-File: LICENSE.txt
Provides-Extra: dev
Requires-Dist: Flask; extra == "dev"
Requires-Dist: google-cloud-secret-manager; extra == "dev"
Requires-Dist: pydantic; extra == "dev"
Requires-Dist: SQLAlchemy; extra == "dev"
Provides-Extra: test
Requires-Dist: Flask; extra == "test"
Requires-Dist: coverage; extra == "test"
Requires-Dist: pytest; extra == "test"
Requires-Dist: pytest-asyncio; extra == "test"
Requires-Dist: pydantic; extra == "test"
Requires-Dist: SQLAlchemy; extra == "test"
Provides-Extra: gcp
Requires-Dist: google-cloud-secret-manager>=2.16.1; extra == "gcp"
Dynamic: license-file
